chmp/cb.py
chmp/ds.py
chmp/parser.py
chmp/rl/__init__.py
chmp/tools/__init__.py
chmp/tools/__main__.py
chmp/tools/mddocs.py
chmp/tools/papers.py
chmp/tools/profiler.py
chmp/torch_utils/__init__.py
chmp/torch_utils/_net.py
chmp/torch_utils/engine.py
chmp-21.8.1.dist-info/METADATA
chmp-21.8.1.dist-info/WHEEL
chmp-21.8.1.dist-info/top_level.txt
chmp-21.8.1.dist-info/RECORD
