Metadata-Version: 2.1
Name: chmp
Version: 21.8.1
Summary: Support code for machine learning / data science experiments
Home-page: https://github.com/chmp/misc-exp
Author: Christopher Prohm
License: UNKNOWN
Platform: UNKNOWN
Classifier: Programming Language :: Python :: 3
Classifier: License :: OSI Approved :: MIT License
Classifier: Operating System :: OS Independent
